standard_evaluator/__init__.py
standard_evaluator/additional_component_options_test.json
standard_evaluator/additional_options.json
standard_evaluator/aviary_encoder.py
standard_evaluator/circuit_example.py
standard_evaluator/converters.py
standard_evaluator/evaluator.py
standard_evaluator/om_converter.py
standard_evaluator/problem.py
standard_evaluator/standard_base.py
standard_evaluator/standard_evaluator.py
standard_evaluator/standard_group.py
standard_evaluator/system_description_to_json.py
standard_evaluator/utilities.py
standard_evaluator/version.py
standard_evaluator-0.2.5.dist-info/licenses/LICENSE
standard_evaluator-0.2.5.dist-info/METADATA
standard_evaluator-0.2.5.dist-info/WHEEL
standard_evaluator-0.2.5.dist-info/top_level.txt
standard_evaluator-0.2.5.dist-info/RECORD
