Metadata-Version: 2.4
Name: standard_evaluator
Version: 0.2.5
Summary: Project description
Author-email: joerg.m.gablonsky@boeing.com
Classifier: Programming Language :: Python :: 3
Classifier: Operating System :: OS Independent
Classifier: License :: OSI Approved :: Apache Software License
Requires-Python: >=3.7
License-File: LICENSE
Requires-Dist: numpy
Requires-Dist: openmdao
Requires-Dist: aviary
Requires-Dist: json-numpy
Requires-Dist: pydantic
Requires-Dist: h5py
Requires-Dist: numpydantic>=1.6.9
Provides-Extra: test
Requires-Dist: pytest; extra == "test"
Requires-Dist: pytest-cov; extra == "test"
Requires-Dist: coverage; extra == "test"
Provides-Extra: dev
Requires-Dist: pytest; extra == "dev"
Requires-Dist: pytest-cov; extra == "dev"
Requires-Dist: coverage; extra == "dev"
Requires-Dist: black; extra == "dev"
Requires-Dist: flake8; extra == "dev"
Requires-Dist: jupyter; extra == "dev"
Provides-Extra: docs
Requires-Dist: pytest; extra == "docs"
Requires-Dist: pytest-cov; extra == "docs"
Requires-Dist: coverage; extra == "docs"
Requires-Dist: black; extra == "docs"
Requires-Dist: flake8; extra == "docs"
Requires-Dist: sphinx; extra == "docs"
Requires-Dist: jupyter; extra == "docs"
Requires-Dist: autodocsumm; extra == "docs"
Requires-Dist: pytest-cov; extra == "docs"
Requires-Dist: sphinxcontrib-mermaid; extra == "docs"
Requires-Dist: sphinx-rtd-theme; extra == "docs"
Requires-Dist: jupyter_core<=5.1.0; extra == "docs"
Requires-Dist: myst-nb; extra == "docs"
Dynamic: license-file
